dorado/sensitivity/__init__.py
dorado/sensitivity/backgrounds.py
dorado/sensitivity/bandpasses.py
dorado/sensitivity/constants.py
dorado/sensitivity/data/__init__.py
dorado/sensitivity/data/leinert_zodi.txt
dorado/sensitivity/data/nuv_d_baseline_effective_area.ecsv
dorado/sensitivity/data/nuv_d_cbe_effective_area.ecsv
dorado/sensitivity/data/nuv_d_threshold_effective_area.ecsv
dorado/sensitivity/data/stis_zodi_high.ecsv
dorado/sensitivity/tests/__init__.py
dorado/sensitivity/tests/test_sensitivity.py
dorado_sensitivity-0.4.0.dist-info/LICENSE.txt
dorado_sensitivity-0.4.0.dist-info/METADATA
dorado_sensitivity-0.4.0.dist-info/WHEEL
dorado_sensitivity-0.4.0.dist-info/entry_points.txt
dorado_sensitivity-0.4.0.dist-info/RECORD
