Metadata-Version: 2.1
Name: dorado-sensitivity
Version: 0.4.0
Summary: Dorado sensitivity and exposure time calculator
Home-page: https://github.com/nasa/dorado-sensitivity
License: NOSA
Author: Brad Cenko
Author-email: brad.cenko@nasa.gov
Requires-Python: >=3.9,<4.0
Classifier: Development Status :: 3 - Alpha
Classifier: Intended Audience :: Science/Research
Classifier: License :: OSI Approved
Classifier: License :: Other/Proprietary License
Classifier: Programming Language :: Python :: 3
Classifier: Programming Language :: Python :: 3.9
Classifier: Programming Language :: Python :: 3.10
Classifier: Programming Language :: Python :: 3.11
Classifier: Programming Language :: Python :: 3.12
Classifier: Programming Language :: Python :: 3 :: Only
Classifier: Topic :: Scientific/Engineering :: Astronomy
Requires-Dist: dust_extinction (>=0.8)
Requires-Dist: dustmaps (>=1.0.8)
Requires-Dist: pyyaml
Requires-Dist: scipy
Requires-Dist: synphot
Project-URL: Bug Tracker, https://github.com/nasa/dorado-sensitivity/issues
Project-URL: Change Log, https://github.com/nasa/dorado-sensitivity/blob/master/CHANGES.md
Project-URL: Repository, https://github.com/nasa/dorado-sensitivity
